{
  "kind": "PNPODirectBindingGapSeed0",
  "version": 0,
  "coordinate": "PNP-DIRECT-BIND-O-ORACLE-ZEROSLACK-GAP-SEED-2026-06-27-01",
  "title": "O theorem direct-binding gap-transition seed",
  "purpose": "Bind the historical Section 22 O theorem-ledger row to current rank-parametric oracle, ZeroSlack, residual-band minimization, complexity implication ledger, finite-to-unbounded audit, gap-ledger, coverage matrix, closure plan, and non-activation surfaces while preserving the active unrestricted-final-soundness blockers.",
  "status": "o-direct-binding-gap-seed-ready",
  "claimBoundary": {
    "publicTheoremEmissionAllowed": false,
    "finalTheoremReady": false,
    "activeFinalNodeIds": [],
    "remainingBlockers": ["Release.UnrestrictedFinalSoundness", "ExternalReview.Acceptance"]
  },
  "oDirectBindingGapSeedReady": true,
  "directCheckerBindingComplete": false,
  "fullHistoricalOTheoremDischarged": false,
  "publicTheoremEmissionAllowedByBinding": false,
  "directBindingBlockedByGaps": true,
  "linkedCoordinates": {
    "reportTheoremInventory": "PNP-REPORT-THEOREM-INVENTORY-2026-06-27-01",
    "reportTheoremCoverageMatrix": "PNP-REPORT-THEOREM-COVERAGE-MATRIX-2026-06-27-01",
    "reportTheoremCoverageClosurePlan": "PNP-REPORT-THEOREM-COVERAGE-CLOSURE-PLAN-2026-06-27-01",
    "complexityLedger": "PNP-COMPLEXITY-LEDGER-2026-06-27-01",
    "gapLedger": "PNP-GAP-LEDGER-2026-06-27-01",
    "finiteToUnboundedFamilyAudit": "PNP-FINITE-TO-UNBOUNDED-FAMILY-AUDIT-2026-06-27-01"
  },
  "boundInventoryEntry": {
    "inventoryEntryId": "TL-024-O",
    "coverageEntryId": "COV-024-O",
    "closureEntryId": "DCC-024-O",
    "sourceLabel": "O",
    "expectedCoverageClass": "complexity-and-gap-surface",
    "expectedClosureStatus": "blocked-by-unrestricted-final-soundness",
    "expectedNextDirectBindingSurface": "pcc-direct-bind-oracle-zeroslack0.mjs"
  },
  "blockingGaps": ["GAP-001-UnrestrictedFinalSoundness", "GAP-004-FiniteToUnboundedUniformity"],
  "coveredOComponents": [
    "O.RankOrderedOracleSurface",
    "O.NoLowerLedgerSurface",
    "O.SelectorSilenceSurface",
    "O.ZeroSlackContradictionSurface",
    "O.ResidualBandExactMinimizationSurface",
    "O.ComplexityConditionalSurface",
    "O.FiniteToUnboundedGapSurface",
    "O.ActivationBoundary"
  ],
  "evidenceSurfaces": [
    "report-bindings/direct-bindings/O_DIRECT_BINDING_GAP_SEED.json",
    "report-bindings/direct-bindings/O_DIRECT_BINDING_GAP_SEED.md",
    "report-bindings/REPORT_THEOREM_INVENTORY.json",
    "report-bindings/REPORT_THEOREM_COVERAGE_MATRIX.json",
    "report-bindings/REPORT_THEOREM_COVERAGE_CLOSURE_PLAN.json",
    "complexity/COMPLEXITY_LEDGER.json",
    "proof-obligations/GAP_LEDGER.json",
    "proof-obligations/FINITE_TO_UNBOUNDED_FAMILY_AUDIT.json",
    "pcc-direct-bind-oracle-zeroslack0.mjs",
    "audits/direct-bind-oracle-zeroslack0.test.mjs",
    "PNP_STATUS.json"
  ],
  "nonClaims": [
    "This O seed does not activate public theorem emission.",
    "This O seed does not clear Release.UnrestrictedFinalSoundness or ExternalReview.Acceptance.",
    "This O seed records a blocked complexity-and-gap transition surface rather than a completed direct checker binding.",
    "This O seed does not prove finite-to-unbounded uniformity or unrestricted residual-band exact minimization."
  ],
  "audit": {
    "checker": "CheckODirectBindingGapSeed0",
    "script": "pcc-direct-bind-oracle-zeroslack0.mjs",
    "test": "audits/direct-bind-oracle-zeroslack0.test.mjs",
    "expectedAcceptTag": "accept"
  }
}
